{
  "id": "9a7957e7-f62f-45c9-a76a-523e840320c4",
  "prevId": "8408bdd2-a881-40c9-ae4c-780a64df4984",
  "version": "7",
  "dialect": "postgresql",
  "tables": {
    "public.questions": {
      "name": "questions",
      "schema": "",
      "columns": {
        "id": {
          "name": "id",
          "type": "uuid",
          "primaryKey": true,
          "notNull": true,
          "default": "gen_random_uuid()"
        },
        "index": {
          "name": "index",
          "type": "integer",
          "primaryKey": false,
          "notNull": false,
          "default": 0
        },
        "title": {
          "name": "title",
          "type": "varchar",
          "primaryKey": false,
          "notNull": true
        },
        "description": {
          "name": "description",
          "type": "text",
          "primaryKey": false,
          "notNull": true
        },
        "correct_answer": {
          "name": "correct_answer",
          "type": "text",
          "primaryKey": false,
          "notNull": true
        },
        "quiz_id": {
          "name": "quiz_id",
          "type": "uuid",
          "primaryKey": false,
          "notNull": true
        }
      },
      "indexes": {},
      "foreignKeys": {
        "questions_quiz_id_quizzes_id_fk": {
          "name": "questions_quiz_id_quizzes_id_fk",
          "tableFrom": "questions",
          "tableTo": "quizzes",
          "columnsFrom": [
            "quiz_id"
          ],
          "columnsTo": [
            "id"
          ],
          "onDelete": "no action",
          "onUpdate": "no action"
        }
      },
      "compositePrimaryKeys": {},
      "uniqueConstraints": {},
      "policies": {},
      "checkConstraints": {},
      "isRLSEnabled": false
    },
    "public.quizzes": {
      "name": "quizzes",
      "schema": "",
      "columns": {
        "id": {
          "name": "id",
          "type": "uuid",
          "primaryKey": true,
          "notNull": true,
          "default": "gen_random_uuid()"
        },
        "title": {
          "name": "title",
          "type": "varchar",
          "primaryKey": false,
          "notNull": true
        },
        "description": {
          "name": "description",
          "type": "text",
          "primaryKey": false,
          "notNull": true
        }
      },
      "indexes": {},
      "foreignKeys": {},
      "compositePrimaryKeys": {},
      "uniqueConstraints": {},
      "policies": {},
      "checkConstraints": {},
      "isRLSEnabled": false
    },
    "public.submissions": {
      "name": "submissions",
      "schema": "",
      "columns": {
        "id": {
          "name": "id",
          "type": "uuid",
          "primaryKey": true,
          "notNull": true,
          "default": "gen_random_uuid()"
        },
        "answer": {
          "name": "answer",
          "type": "text",
          "primaryKey": false,
          "notNull": true
        },
        "user": {
          "name": "user",
          "type": "char",
          "primaryKey": false,
          "notNull": true
        },
        "question_id": {
          "name": "question_id",
          "type": "uuid",
          "primaryKey": false,
          "notNull": true
        }
      },
      "indexes": {},
      "foreignKeys": {
        "submissions_question_id_questions_id_fk": {
          "name": "submissions_question_id_questions_id_fk",
          "tableFrom": "submissions",
          "tableTo": "questions",
          "columnsFrom": [
            "question_id"
          ],
          "columnsTo": [
            "id"
          ],
          "onDelete": "no action",
          "onUpdate": "no action"
        }
      },
      "compositePrimaryKeys": {},
      "uniqueConstraints": {},
      "policies": {},
      "checkConstraints": {},
      "isRLSEnabled": false
    }
  },
  "enums": {},
  "schemas": {},
  "sequences": {},
  "roles": {},
  "policies": {},
  "views": {},
  "_meta": {
    "columns": {},
    "schemas": {},
    "tables": {}
  }
}